aliyunsdkprivatelink/__init__.py
aliyunsdkprivatelink/endpoint.py
aliyunsdkprivatelink/request/__init__.py
aliyunsdkprivatelink/request/v20200415/AddUserToVpcEndpointServiceRequest.py
aliyunsdkprivatelink/request/v20200415/AddZoneToVpcEndpointRequest.py
aliyunsdkprivatelink/request/v20200415/AttachResourceToVpcEndpointServiceRequest.py
aliyunsdkprivatelink/request/v20200415/AttachSecurityGroupToVpcEndpointRequest.py
aliyunsdkprivatelink/request/v20200415/ChangeResourceGroupRequest.py
aliyunsdkprivatelink/request/v20200415/CheckProductOpenRequest.py
aliyunsdkprivatelink/request/v20200415/CheckResourceSupportOperateRequest.py
aliyunsdkprivatelink/request/v20200415/CreateVpcEndpointRequest.py
aliyunsdkprivatelink/request/v20200415/CreateVpcEndpointServiceRequest.py
aliyunsdkprivatelink/request/v20200415/DeleteVpcEndpointRequest.py
aliyunsdkprivatelink/request/v20200415/DeleteVpcEndpointServiceRequest.py
aliyunsdkprivatelink/request/v20200415/DescribeRegionsRequest.py
aliyunsdkprivatelink/request/v20200415/DescribeZonesRequest.py
aliyunsdkprivatelink/request/v20200415/DetachResourceFromVpcEndpointServiceRequest.py
aliyunsdkprivatelink/request/v20200415/DetachSecurityGroupFromVpcEndpointRequest.py
aliyunsdkprivatelink/request/v20200415/DisableVpcEndpointConnectionRequest.py
aliyunsdkprivatelink/request/v20200415/DisableVpcEndpointZoneConnectionRequest.py
aliyunsdkprivatelink/request/v20200415/EnableVpcEndpointConnectionRequest.py
aliyunsdkprivatelink/request/v20200415/EnableVpcEndpointZoneConnectionRequest.py
aliyunsdkprivatelink/request/v20200415/GetVpcEndpointAttributeRequest.py
aliyunsdkprivatelink/request/v20200415/GetVpcEndpointServiceAttributeRequest.py
aliyunsdkprivatelink/request/v20200415/ListVpcEndpointConnectionsRequest.py
aliyunsdkprivatelink/request/v20200415/ListVpcEndpointSecurityGroupsRequest.py
aliyunsdkprivatelink/request/v20200415/ListVpcEndpointServiceResourcesRequest.py
aliyunsdkprivatelink/request/v20200415/ListVpcEndpointServiceUsersRequest.py
aliyun_python_sdk_privatelink-1.0.8.dist-info/LICENSE
aliyun_python_sdk_privatelink-1.0.8.dist-info/METADATA
aliyun_python_sdk_privatelink-1.0.8.dist-info/WHEEL
aliyun_python_sdk_privatelink-1.0.8.dist-info/top_level.txt
aliyun_python_sdk_privatelink-1.0.8.dist-info/RECORD
